aether_helm_generator-1.7.data/scripts/generator.py
helm_generator/__init__.py
helm_generator/args.py
helm_generator/generator.py
helm_generator/secretsGenerator.py
helm_generator/templateGenerator.py
helm_generator/templates/secrets.tmpl.yaml
helm_generator/templates/values.tmpl.yaml
aether_helm_generator-1.7.dist-info/METADATA
aether_helm_generator-1.7.dist-info/WHEEL
aether_helm_generator-1.7.dist-info/entry_points.txt
aether_helm_generator-1.7.dist-info/top_level.txt
aether_helm_generator-1.7.dist-info/RECORD
