Metadata-Version: 2.1
Name: aether-helm-generator
Version: 1.7
Summary: Generate values and secrets for Helm
Home-page: http://github.com/ehealthafrica/aether-bootstrap
Author: Will Pink
Author-email: devops@ehealthafrica.org
License: MIT
Platform: UNKNOWN
Requires-Dist: jinja2
